rglob/__init__.py
rglob/rglob.py
rglob-1.7.dist-info/DESCRIPTION.rst
rglob-1.7.dist-info/METADATA
rglob-1.7.dist-info/RECORD
rglob-1.7.dist-info/WHEEL
rglob-1.7.dist-info/metadata.json
rglob-1.7.dist-info/top_level.txt
