Metadata-Version: 1.2
Name: rglob
Version: 1.7
Summary: Python Recursive Glob
Home-page: http://cpiekarski.com/2011/09/23/python-recursive-glob/
Author: Christopher Piekarski
Author-email: chris@cpiekarski.com
Maintainer: Christopher Piekarski
Maintainer-email: chris@cpiekarski.com
License: OSI Approved Apache Software License
Keywords: glob,rglob,recursive,line counter
Platform: UNKNOWN
Classifier: Intended Audience :: Developers
Classifier: License :: OSI Approved :: Apache Software License
Classifier: Programming Language :: Python :: 3.5
Classifier: Operating System :: OS Independent
Provides: rglob
Requires-Python: >=3.5
